pepperize_cdk_autoscaling_gitlab_runner/__init__.py
pepperize_cdk_autoscaling_gitlab_runner/py.typed
pepperize_cdk_autoscaling_gitlab_runner/_jsii/__init__.py
pepperize_cdk_autoscaling_gitlab_runner/_jsii/cdk-autoscaling-gitlab-runner@0.2.717.jsii.tgz
pepperize_cdk_autoscaling_gitlab_runner-0.2.717.dist-info/LICENSE
pepperize_cdk_autoscaling_gitlab_runner-0.2.717.dist-info/METADATA
pepperize_cdk_autoscaling_gitlab_runner-0.2.717.dist-info/WHEEL
pepperize_cdk_autoscaling_gitlab_runner-0.2.717.dist-info/top_level.txt
pepperize_cdk_autoscaling_gitlab_runner-0.2.717.dist-info/RECORD
