Metadata-Version: 2.1
Name: pepperize.cdk-autoscaling-gitlab-runner
Version: 0.2.717
Summary: AWS CDK GitLab Runner autoscaling on EC2 instances using docker+machine executor.
Home-page: https://github.com/pepperize/cdk-autoscaling-gitlab-runner.git
Author: Patrick Florek<patrick.florek@gmail.com>
License: MIT
Project-URL: Source, https://github.com/pepperize/cdk-autoscaling-gitlab-runner.git
Classifier: Intended Audience :: Developers
Classifier: Operating System :: OS Independent
Classifier: Programming Language :: JavaScript
Classifier: Programming Language :: Python :: 3 :: Only
Classifier: Programming Language :: Python :: 3.9
Classifier: Programming Language :: Python :: 3.10
Classifier: Programming Language :: Python :: 3.11
Classifier: Typing :: Typed
Classifier: Development Status :: 5 - Production/Stable
Classifier: License :: OSI Approved
Requires-Python: ~=3.9
License-File: LICENSE
Requires-Dist: aws-cdk-lib<3.0.0,>=2.8.0
Requires-Dist: constructs<11.0.0,>=10.0.5
Requires-Dist: jsii<2.0.0,>=1.112.0
Requires-Dist: pepperize.cdk-private-bucket<0.0.352,>=0.0.351
Requires-Dist: pepperize.cdk-security-group<0.0.440,>=0.0.439
Requires-Dist: pepperize.cdk-vpc<0.0.559,>=0.0.558
Requires-Dist: publication>=0.0.3
Requires-Dist: typeguard<4.3.0,>=2.13.3
